flufl.bounce-4.0-py3.8-nspkg.pth
flufl/bounce/NEWS.rst
flufl/bounce/README.rst
flufl/bounce/__init__.py
flufl/bounce/_scan.py
flufl/bounce/conf.py
flufl/bounce/interfaces.py
flufl/bounce/_detectors/__init__.py
flufl/bounce/_detectors/aol.py
flufl/bounce/_detectors/caiwireless.py
flufl/bounce/_detectors/dsn.py
flufl/bounce/_detectors/exchange.py
flufl/bounce/_detectors/exim.py
flufl/bounce/_detectors/groupwise.py
flufl/bounce/_detectors/llnl.py
flufl/bounce/_detectors/microsoft.py
flufl/bounce/_detectors/netscape.py
flufl/bounce/_detectors/postfix.py
flufl/bounce/_detectors/qmail.py
flufl/bounce/_detectors/simplematch.py
flufl/bounce/_detectors/simplewarning.py
flufl/bounce/_detectors/sina.py
flufl/bounce/_detectors/smtp32.py
flufl/bounce/_detectors/yahoo.py
flufl/bounce/_detectors/yale.py
flufl/bounce/docs/__init__.py
flufl/bounce/docs/using.rst
flufl/bounce/testing/__init__.py
flufl/bounce/testing/helpers.py
flufl/bounce/tests/__init__.py
flufl/bounce/tests/test_detectors.py
flufl/bounce/tests/data/__init__.py
flufl/bounce/tests/data/aol_01.txt
flufl/bounce/tests/data/bounce_01.txt
flufl/bounce/tests/data/bounce_02.txt
flufl/bounce/tests/data/bounce_03.txt
flufl/bounce/tests/data/dsn_01.txt
flufl/bounce/tests/data/dsn_02.txt
flufl/bounce/tests/data/dsn_03.txt
flufl/bounce/tests/data/dsn_04.txt
flufl/bounce/tests/data/dsn_05.txt
flufl/bounce/tests/data/dsn_06.txt
flufl/bounce/tests/data/dsn_07.txt
flufl/bounce/tests/data/dsn_08.txt
flufl/bounce/tests/data/dsn_09.txt
flufl/bounce/tests/data/dsn_10.txt
flufl/bounce/tests/data/dsn_11.txt
flufl/bounce/tests/data/dsn_12.txt
flufl/bounce/tests/data/dsn_13.txt
flufl/bounce/tests/data/dsn_14.txt
flufl/bounce/tests/data/dsn_15.txt
flufl/bounce/tests/data/dsn_16.txt
flufl/bounce/tests/data/dsn_17.txt
flufl/bounce/tests/data/dsn_18.txt
flufl/bounce/tests/data/dumbass_01.txt
flufl/bounce/tests/data/exim_01.txt
flufl/bounce/tests/data/groupwise_01.txt
flufl/bounce/tests/data/groupwise_02.txt
flufl.bounce-4.0.dist-info/LICENSE
flufl.bounce-4.0.dist-info/METADATA
flufl.bounce-4.0.dist-info/WHEEL
flufl.bounce-4.0.dist-info/namespace_packages.txt
flufl.bounce-4.0.dist-info/top_level.txt
flufl.bounce-4.0.dist-info/RECORD
